[{
	"key": "datr",
	"value": "B3rjaIi_1_hMdyvGblU0nMRV",
	"path": "/",
	"hostOnly": false,
	"domain": ".facebook.com",
	"creation": "2025-10-06T15:59:54.418Z",
	"lastAccessed": "2025-10-06T15:59:54.418Z"
	},
	{
	"key": "sb",
	"value": "B3rjaA7LL9hydPUsUrPo8Cwv",
	"path": "/",
	"hostOnly": false,
	"domain": ".facebook.com",
	"creation": "2025-10-06T15:59:54.418Z",
	"lastAccessed": "2025-10-06T15:59:54.418Z"
	},
	{
	"key": "m_pixel_ratio",
	"value": "1.7000000476837158",
	"path": "/",
	"hostOnly": false,
	"domain": ".facebook.com",
	"creation": "2025-10-06T15:59:54.418Z",
	"lastAccessed": "2025-10-06T15:59:54.418Z"
	},
	{
	"key": "c_user",
	"value": "61582027311503",
	"path": "/",
	"hostOnly": false,
	"domain": ".facebook.com",
	"creation": "2025-10-06T15:59:54.418Z",
	"lastAccessed": "2025-10-06T15:59:54.418Z"
	},
	{
	"key": "xs",
	"value": "32%3AnhRV1CTTVaYuvQ%3A2%3A1759738392%3A-1%3A-1",
	"path": "/",
	"hostOnly": false,
	"domain": ".facebook.com",
	"creation": "2025-10-06T15:59:54.418Z",
	"lastAccessed": "2025-10-06T15:59:54.418Z"
	},
	{
	"key": "locale",
	"value": "en_US",
	"path": "/",
	"hostOnly": false,
	"domain": ".facebook.com",
	"creation": "2025-10-06T15:59:54.418Z",
	"lastAccessed": "2025-10-06T15:59:54.418Z"
	},
	{
	"key": "pas",
	"value": "61582027311503%3AUj27oatqts",
	"path": "/",
	"hostOnly": false,
	"domain": ".facebook.com",
	"creation": "2025-10-06T15:59:54.418Z",
	"lastAccessed": "2025-10-06T15:59:54.418Z"
	},
	{
	"key": "vpd",
	"value": "v1%3B845x423x1.7000000476837158",
	"path": "/",
	"hostOnly": false,
	"domain": ".facebook.com",
	"creation": "2025-10-06T15:59:54.418Z",
	"lastAccessed": "2025-10-06T15:59:54.418Z"
	},
	{
	"key": "dpr",
	"value": "1.7000000476837158",
	"path": "/",
	"hostOnly": false,
	"domain": ".facebook.com",
	"creation": "2025-10-06T15:59:54.418Z",
	"lastAccessed": "2025-10-06T15:59:54.418Z"
	},
	{
	"key": "wd",
	"value": "424x942",
	"path": "/",
	"hostOnly": false,
	"domain": ".facebook.com",
	"creation": "2025-10-06T15:59:54.418Z",
	"lastAccessed": "2025-10-06T15:59:54.418Z"
	},
	{
	"key": "fr",
	"value": "0VUqdClvcBVoUFf1l.AWfWHb-anOWgQUDLF870SyORneHlcvBWXOXFZ4HaGmvjUr2KHkY.Bo43oH..AAA.0.0.Bo4-dx.AWfI34X1r0uOyDZYBrHe8pB7iH0",
	"path": "/",
	"hostOnly": false,
	"domain": ".facebook.com",
	"creation": "2025-10-06T15:59:54.418Z",
	"lastAccessed": "2025-10-06T15:59:54.418Z"
	},
	{
	"key": "fbl_st",
	"value": "100623315%3BT%3A29329439",
	"path": "/",
	"hostOnly": false,
	"domain": ".facebook.com",
	"creation": "2025-10-06T15:59:54.418Z",
	"lastAccessed": "2025-10-06T15:59:54.418Z"
	},
	{
	"key": "wl_cbv",
	"value": "v2%3Bclient_version%3A2944%3Btimestamp%3A1759766385",
	"path": "/",
	"hostOnly": false,
	"domain": ".facebook.com",
	"creation": "2025-10-06T15:59:54.418Z",
	"lastAccessed": "2025-10-06T15:59:54.418Z"
	}]
